src/__init__.py
src/main.py
src/config/__init__.py
src/config/config_manager.py
src/config/settings.py
src/database/__init__.py
src/database/db_manager.py
src/database/migrations.py
src/models/__init__.py
src/models/portfolio.py
src/models/stock.py
src/models/transaction.py
src/services/__init__.py
src/services/chart_service.py
src/services/google_auth.py
src/services/google_services.py
src/services/portfolio_manager.py
src/services/stock_service.py
src/services/system_service.py
src/services/weather_service.py
src/widgets/__init__.py
src/widgets/chart_view.py
src/widgets/google_panel.py
src/widgets/portfolio_modal.py
src/widgets/portfolio_table.py
src/widgets/settings_modal.py
src/widgets/stock_modal.py
xengom_dash-0.1.0.dist-info/METADATA
xengom_dash-0.1.0.dist-info/WHEEL
xengom_dash-0.1.0.dist-info/entry_points.txt
xengom_dash-0.1.0.dist-info/top_level.txt
xengom_dash-0.1.0.dist-info/RECORD
