Metadata-Version: 2.4
Name: xengom-dash
Version: 0.1.0
Summary: Personal dashboard TUI application with portfolio management, system monitoring, and weather information
Author-email: xengom <xengom@gmail.com>
Maintainer-email: xengom <xengom@gmail.com>
License: MIT
Project-URL: Homepage, https://github.com/xengom/mydash
Project-URL: Repository, https://github.com/xengom/mydash
Project-URL: Issues, https://github.com/xengom/mydash/issues
Project-URL: Documentation, https://github.com/xengom/mydash#readme
Keywords: tui,dashboard,portfolio,stocks,terminal,textual,monitoring
Classifier: Development Status :: 4 - Beta
Classifier: Environment :: Console
Classifier: Intended Audience :: End Users/Desktop
Classifier: License :: OSI Approved :: MIT License
Classifier: Operating System :: OS Independent
Classifier: Programming Language :: Python :: 3
Classifier: Programming Language :: Python :: 3.10
Classifier: Programming Language :: Python :: 3.11
Classifier: Programming Language :: Python :: 3.12
Classifier: Programming Language :: Python :: 3.13
Classifier: Topic :: Office/Business :: Financial :: Investment
Classifier: Topic :: System :: Monitoring
Classifier: Topic :: Terminals
Requires-Python: >=3.10
Requires-Dist: textual>=0.47.0
Requires-Dist: rich>=13.7.0
Requires-Dist: yfinance>=0.2.40
Requires-Dist: pandas>=2.2.0
Requires-Dist: numpy>=1.26.0
Requires-Dist: google-api-python-client>=2.110.0
Requires-Dist: google-auth-httplib2>=0.2.0
Requires-Dist: google-auth-oauthlib>=1.2.0
Requires-Dist: psutil>=5.9.6
Requires-Dist: requests>=2.31.0
Requires-Dist: python-dotenv>=1.0.0
Requires-Dist: plotext>=5.2.8
Provides-Extra: dev
Requires-Dist: pytest>=7.4.3; extra == "dev"
Requires-Dist: pytest-asyncio>=0.23.2; extra == "dev"
Requires-Dist: black>=23.12.0; extra == "dev"
Requires-Dist: ruff>=0.1.8; extra == "dev"
